bencodex/__init__.py
bencodex/py.typed
bencodex/reader.py
bencodex/test.py
bencodex/types.py
bencodex/writer.py
bencodex/spec/testsuite/bigint.dat
bencodex/spec/testsuite/bigint.yaml
bencodex/spec/testsuite/byte-string.dat
bencodex/spec/testsuite/byte-string.yaml
bencodex/spec/testsuite/bytestring-dict.dat
bencodex/spec/testsuite/bytestring-dict.yaml
bencodex/spec/testsuite/empty-byte-string.dat
bencodex/spec/testsuite/empty-byte-string.yaml
bencodex/spec/testsuite/empty-dict.dat
bencodex/spec/testsuite/empty-dict.yaml
bencodex/spec/testsuite/empty-list.dat
bencodex/spec/testsuite/empty-list.yaml
bencodex/spec/testsuite/empty-unicode-string.dat
bencodex/spec/testsuite/empty-unicode-string.yaml
bencodex/spec/testsuite/false.dat
bencodex/spec/testsuite/false.yaml
bencodex/spec/testsuite/list-4sprouts.dat
bencodex/spec/testsuite/list-4sprouts.yaml
bencodex/spec/testsuite/list-of-dicts.dat
bencodex/spec/testsuite/list-of-dicts.yaml
bencodex/spec/testsuite/list.dat
bencodex/spec/testsuite/list.yaml
bencodex/spec/testsuite/mixed-dict.dat
bencodex/spec/testsuite/mixed-dict.yaml
bencodex/spec/testsuite/natural-number.dat
bencodex/spec/testsuite/natural-number.yaml
bencodex/spec/testsuite/negative-number.dat
bencodex/spec/testsuite/negative-number.yaml
bencodex/spec/testsuite/nested-dict.dat
bencodex/spec/testsuite/nested-dict.yaml
bencodex/spec/testsuite/null.dat
bencodex/spec/testsuite/null.yaml
bencodex/spec/testsuite/true.dat
bencodex/spec/testsuite/true.yaml
bencodex/spec/testsuite/unicode-dict.dat
bencodex/spec/testsuite/unicode-dict.yaml
bencodex/spec/testsuite/unicode-string.dat
bencodex/spec/testsuite/unicode-string.yaml
bencodex/spec/testsuite/zero.dat
bencodex/spec/testsuite/zero.yaml
bencodex-1.0.1.dist-info/METADATA
bencodex-1.0.1.dist-info/RECORD
bencodex-1.0.1.dist-info/WHEEL
bencodex-1.0.1.dist-info/top_level.txt
